coverage_python_version/__init__.py
coverage_python_version-0.2.0.dist-info/LICENSE.rst
coverage_python_version-0.2.0.dist-info/METADATA
coverage_python_version-0.2.0.dist-info/WHEEL
coverage_python_version-0.2.0.dist-info/top_level.txt
coverage_python_version-0.2.0.dist-info/zip-safe
coverage_python_version-0.2.0.dist-info/RECORD
