Metadata-Version: 2.1
Name: coverage-python-version
Version: 0.2.0
Summary: A coverage.py plugin to facilitate exclusions based on Python version
Home-page: https://github.com/jayclassless/coverage_python_version
Author: Jason Simeone
Author-email: jay@classless.net
License: MIT
Keywords: coverage plugin version exclude
Platform: UNKNOWN
Classifier: Intended Audience :: Developers
Classifier: License :: OSI Approved :: MIT License
Classifier: Programming Language :: Python
Classifier: Programming Language :: Python :: 2.7
Classifier: Programming Language :: Python :: 3.4
Classifier: Programming Language :: Python :: 3.5
Classifier: Programming Language :: Python :: 3.6
Classifier: Programming Language :: Python :: 3.7
Classifier: Programming Language :: Python :: 3.8
Classifier: Programming Language :: Python :: Implementation :: CPython
Classifier: Programming Language :: Python :: Implementation :: PyPy
Classifier: Topic :: Software Development
Classifier: Topic :: Software Development :: Testing
Requires-Dist: coverage (<6,>=4.5)
